LICENSE
README.md
Table_Differ/.DS_Store
Table_Differ/configs/deprecated.yaml
Table_Differ/configs/example.yaml
Table_Differ/data_profiler_notebook.py
Table_Differ/modules/create_diff_table.py
Table_Differ/modules/db_utils.py
Table_Differ/modules/exceptions.py
Table_Differ/modules/get_config.py
Table_Differ/modules/gnome.py
Table_Differ/modules/pydantic_models.py
Table_Differ/modules/reporting.py
Table_Differ/table_differ.py
Table_Differ/table_differ_notebook.py
configs/example.yaml
table_differ-0.2.2.dist-info/LICENSE
table_differ-0.2.2.dist-info/METADATA
table_differ-0.2.2.dist-info/WHEEL
table_differ-0.2.2.dist-info/RECORD
