Metadata-Version: 2.1
Name: table-differ
Version: 0.2.2
Summary: cross-platform table-diffing utility
License: MIT
Author: Benjamin Farmer
Author-email: benjamin@sanjuandata.com
Requires-Python: >=3.10,<4.0
Classifier: License :: OSI Approved :: MIT License
Classifier: Programming Language :: Python :: 3
Classifier: Programming Language :: Python :: 3.10
Classifier: Programming Language :: Python :: 3.11
Classifier: Programming Language :: Python :: 3.12
Requires-Dist: databricks-connect (>=15.4.2,<16.0.0)
Requires-Dist: duckdb (>=1.1.2,<2.0.0)
Requires-Dist: pydantic (>=2.9.2,<3.0.0)
Requires-Dist: pytest (>=8.3.2,<9.0.0)
Requires-Dist: pyyaml (==6.0.1)
Requires-Dist: rich (==13.5.2)
